Workbook

Sheet How to Use
A1: HOW TO USE | Staff Payroll Sheet | Digitglance Reliance
A2: Yellow cells = enter your data | Green cells = auto-calculated (do not edit) | Read each step before you begin
A4: Step 1: School & Month — Enter school name, month, year and PFA name in the header section
A5: Step 2: Staff Roster — Enter each staff member's name, designation, department and grade level
A6: Step 3: Basic Salary — Enter the gross monthly basic salary for each staff member in Column E
A7: Step 4: Allowances — Enter housing, transport and other allowances in Columns F, G and H
A8: Step 5: Gross Pay — Auto-calculates: Basic + All Allowances — do not edit
A9: Step 6: Pension — Employee pension deducted at 8% of (Basic + Housing) per PRA 2004/2014
A10: Step 7: NHF — National Housing Fund = 2.5% of Basic Salary (formal employees only)
A11: Step 8: PAYE Tax — Estimated PAYE based on simplified Nigerian tax bands — verify with your LIRS/FIRS
A12: Step 9: Net Pay — Auto-calculates: Gross minus Pension minus NHF minus PAYE minus Other Deductions
A13: Step 10: Employer Pension — Employer contributes 10% of (Basic + Housing) — shown separately for PENCOM remittance

Sheet Staff Payroll Sheet
A1: DIGITGLANCE RELIANCE | Staff Payroll Sheet
A2: School | Monthly staff salary computation — allowances, pension, PAYE, NHF, net pay | N
A3: School Name: _______________________________________________ | H3: Date: 26/04/2026 | www.digitglance.com
A5: School Name: | B5: St. Gabriel's International School, Abuja
A6: Month:
A7: Year:
A8: PFA Name: | B8: Stanbic IBTC Pension Managers Ltd
A9: Total Staff:
A11: # | B11: Staff Name | C11: Designation | D11: Dept. | E11: Basic Salary (N) | F11: Housing Allow. (N) | G11: Transport Allow. (N) | H11: Other Allow. (N) | I11: Gross Pay (N) | J11: Employee Pension 8% (N) | K11: NHF 2.5% (N) | L11: PAYE Tax (N) | M11: Other Deduct. (N) | N11: NET PAY (N) | O11: Employer Pension 10% (N)
A12: 1 | B12: Mrs. Adaobi Okafor | C12: Principal | D12: Management | I12: =E12+F12+G12+H12 | J12: =(E12+F12)*0.08 | K12: =E12*0.025 | L12: =MAX(0,ROUND((I12-J12-K12-MAX(I12*0.20,16667))*0.07,0)) | N12: =I12-J12-K12-L12-M12 | O12: =(E12+F12)*0.10
A13: 2 | B13: Mr. Emeka Eze | C13: Vice Principal (Admin) | D13: Management | I13: =E13+F13+G13+H13 | J13: =(E13+F13)*0.08 | K13: =E13*0.025 | L13: =MAX(0,ROUND((I13-J13-K13-MAX(I13*0.20,16667))*0.07,0)) | N13: =I13-J13-K13-L13-M13 | O13: =(E13+F13)*0.10
A14: 3 | B14: Mrs. Chioma Obi | C14: Vice Principal (Acad.) | D14: Management | I14: =E14+F14+G14+H14 | J14: =(E14+F14)*0.08 | K14: =E14*0.025 | L14: =MAX(0,ROUND((I14-J14-K14-MAX(I14*0.20,16667))*0.07,0)) | N14: =I14-J14-K14-L14-M14 | O14: =(E14+F14)*0.10
A15: 4 | B15: Mr. Tunde Adeyemi | C15: Mathematics Teacher | D15: Academic | I15: =E15+F15+G15+H15 | J15: =(E15+F15)*0.08 | K15: =E15*0.025 | L15: =MAX(0,ROUND((I15-J15-K15-MAX(I15*0.20,16667))*0.07,0)) | N15: =I15-J15-K15-L15-M15 | O15: =(E15+F15)*0.10
A16: 5 | B16: Miss Fatimah Lawal | C16: English Language Tchr | D16: Academic | I16: =E16+F16+G16+H16 | J16: =(E16+F16)*0.08 | K16: =E16*0.025 | L16: =MAX(0,ROUND((I16-J16-K16-MAX(I16*0.20,16667))*0.07,0)) | N16: =I16-J16-K16-L16-M16 | O16: =(E16+F16)*0.10
A17: 6 | B17: Mr. Uche Nwosu | C17: Physics Teacher | D17: Academic | I17: =E17+F17+G17+H17 | J17: =(E17+F17)*0.08 | K17: =E17*0.025 | L17: =MAX(0,ROUND((I17-J17-K17-MAX(I17*0.20,16667))*0.07,0)) | N17: =I17-J17-K17-L17-M17 | O17: =(E17+F17)*0.10
A18: 7 | B18: Mrs. Ngozi Anyanwu | C18: Biology Teacher | D18: Academic | I18: =E18+F18+G18+H18 | J18: =(E18+F18)*0.08 | K18: =E18*0.025 | L18: =MAX(0,ROUND((I18-J18-K18-MAX(I18*0.20,16667))*0.07,0)) | N18: =I18-J18-K18-L18-M18 | O18: =(E18+F18)*0.10
A19: 8 | B19: Mr. Suleiman Ahmed | C19: Chemistry Teacher | D19: Academic | I19: =E19+F19+G19+H19 | J19: =(E19+F19)*0.08 | K19: =E19*0.025 | L19: =MAX(0,ROUND((I19-J19-K19-MAX(I19*0.20,16667))*0.07,0)) | N19: =I19-J19-K19-L19-M19 | O19: =(E19+F19)*0.10
A20: 9 | B20: Miss Amina Bello | C20: French Teacher | D20: Academic | I20: =E20+F20+G20+H20 | J20: =(E20+F20)*0.08 | K20: =E20*0.025 | L20: =MAX(0,ROUND((I20-J20-K20-MAX(I20*0.20,16667))*0.07,0)) | N20: =I20-J20-K20-L20-M20 | O20: =(E20+F20)*0.10
A21: 10 | B21: Mr. Olu Fashola | C21: P.E. Teacher | D21: Academic | I21: =E21+F21+G21+H21 | J21: =(E21+F21)*0.08 | K21: =E21*0.025 | L21: =MAX(0,ROUND((I21-J21-K21-MAX(I21*0.20,16667))*0.07,0)) | N21: =I21-J21-K21-L21-M21 | O21: =(E21+F21)*0.10
A22: 11 | B22: Mrs. Grace Effiong | C22: Primary Class Tchr 1 | D22: Academic | I22: =E22+F22+G22+H22 | J22: =(E22+F22)*0.08 | K22: =E22*0.025 | L22: =MAX(0,ROUND((I22-J22-K22-MAX(I22*0.20,16667))*0.07,0)) | N22: =I22-J22-K22-L22-M22 | O22: =(E22+F22)*0.10
A23: 12 | B23: Mr. Yusuf Garba | C23: Bursar | D23: Admin/Finance | I23: =E23+F23+G23+H23 | J23: =(E23+F23)*0.08 | K23: =E23*0.025 | L23: =MAX(0,ROUND((I23-J23-K23-MAX(I23*0.20,16667))*0.07,0)) | N23: =I23-J23-K23-L23-M23 | O23: =(E23+F23)*0.10
... A31: 20 | B31: Mr. Babatunde Olusanya | C31: Maintenance Supervisor | D31: Support | I31: =E31+F31+G31+H31 | J31: =(E31+F31)*0.08 | K31: =E31*0.025 | L31: =MAX(0,ROUND((I31-J31-K31-MAX(I31*0.20,16667))*0.07,0)) | N31: =I31-J31-K31-L31-M31 | O31: =(E31+F31)*0.10
B32: MONTHLY TOTALS | E32: =SUM(E12:E31) | F32: =SUM(F12:F31) | G32: =SUM(G12:G31) | H32: =SUM(H12:H31) | I32: =SUM(I12:I31) | J32: =SUM(J12:J31) | K32: =SUM(K12:K31) | L32: =SUM(L12:L31) | ... O32: =SUM(O12:O31)
A35: PENCOM REMITTANCE: Employee contribution (8%) + Employer contribution (10%) = Total 18% of Pensionable Pay. Remit monthly to your PFA within 7 days of salary payment. PAYE: Remit to LIRS (Lagos) or FIRS within 10 days of month end. NHF: Remit to Federal Mortgage Bank of Nigeria (FMBN) monthly.

Sheet Payroll Summary
A1: DIGITGLANCE RELIANCE | Monthly Payroll Summary
A2: School | Totals by department and statutory deduction breakdown
A3: School Name: _______________________________________________ | E3: Date: 26/04/2026 | www.digitglance.com
A5: PAYROLL COST SUMMARY
A7: Total Gross Pay (N) | E7: ='Staff Payroll Sheet'!I32
A8: Total Employee Pension (N) | E8: ='Staff Payroll Sheet'!J32
A9: Total NHF Deduction (N) | E9: ='Staff Payroll Sheet'!K32
A10: Total PAYE Tax (N) | E10: ='Staff Payroll Sheet'!L32
A11: Total Net Pay (N) | E11: ='Staff Payroll Sheet'!N32
A12: Total Employer Pension (N) | E12: ='Staff Payroll Sheet'!O32
A13: Total Payroll Cost (N) | E13: ='Staff Payroll Sheet'!I32+'Staff Payroll Sheet'!O32
